stocklerain1001/__init__.py
stocklerain1001/stocklerain1001.py
stocklerain1001-0.0.1.dist-info/LICENSE
stocklerain1001-0.0.1.dist-info/METADATA
stocklerain1001-0.0.1.dist-info/WHEEL
stocklerain1001-0.0.1.dist-info/top_level.txt
stocklerain1001-0.0.1.dist-info/RECORD
