Metadata-Version: 2.1
Name: stocklerain1001
Version: 0.0.1
Summary: Stock information analysis package
Author: Abdurrahman Al-boti
Author-email: <abdurrahman.alboti@bahcesehir.edu.tr>
Keywords: python,stock,finance,SMA,RSI
Classifier: Programming Language :: Python :: 3
Classifier: Operating System :: OS Independent
License-File: LICENSE
